stubbles/__init__.py
stubbles/__main__.py
stubbles/inputs.py
stubbles/templates.py
stubbles/tests/__init__.py
stubbles/tests/data/example.cpp
stubbles/tests/data/example.h
stubbles/tests/data/example.py
stubbles/tests/replacements.json
stubbles/tests/test_inputs.py
stubbles/tests/test_main.py
stubbles/tests/test_templates.py
stubbles/tests/test_types.py
stubbles/types.py
stubbles-1.0.0.dist-info/LICENSE
stubbles-1.0.0.dist-info/METADATA
stubbles-1.0.0.dist-info/WHEEL
stubbles-1.0.0.dist-info/RECORD
