Metadata-Version: 2.1
Name: stubbles
Version: 1.0.0
Summary: Inline seamless code generation
License: MIT
Author: Jordan Edmunds
Requires-Python: >=3.8,<4.0
Classifier: License :: OSI Approved :: MIT License
Classifier: Programming Language :: Python :: 3
Classifier: Programming Language :: Python :: 3.8
Classifier: Programming Language :: Python :: 3.9
Classifier: Programming Language :: Python :: 3.10
Classifier: Programming Language :: Python :: 3.11
Requires-Dist: click (>=8.1.7,<9.0.0)
Requires-Dist: pyyaml (>=6.0.1,<7.0.0)
Requires-Dist: toml (>=0.10.2,<0.11.0)
